[
    {
        "username": "personnew",
        "password": "$2y$10$Ph.56h2HRFcSbTypJiio5u\/dkuN3GYb7p0JW0BBRLc.dcWu1n8noC",
        "address": "amman",
        "country": "jordan",
        "code": "123",
        "email": "person2@ex.com",
        "sex": "female",
        "checkbox": "english",
        "about": "test"
    },
    {
        "username": "person1",
        "password": "$2y$10$lA3y7vYJeh3NEBxazppve.\/GHxuu35KxEaFR1bTZaLfRHSx7Xsmu2",
        "address": "amman",
        "country": "jordan",
        "code": "123",
        "email": "person1@ex.com",
        "sex": "male",
        "checkbox": "english",
        "about": "test"
    },
    {
        "username": "test123",
        "password": "$2y$10$5lj81SG7.KPCiCHlamS4sOzcHdd8NrgCS5Jpezictv0U2qPHLMZVO",
        "address": "amman",
        "country": "jordan",
        "code": "234",
        "email": "test123@ex.com",
        "sex": "female",
        "checkbox": "english",
        "about": "asdfgf"
    },
    {
        "username": "samia",
        "password": "$2y$10$R5AV95RmGJtT\/nTw1N6JAegNJCGWvFKuyiQVUDsNIpiYy9Im.fgMy",
        "address": "amman",
        "country": "jordan",
        "code": "123",
        "email": "samia@ex.com",
        "sex": "female",
        "checkbox": "english",
        "about": "Samia@12345"
    },
    {
        "username": "testing",
        "password": "$2y$10$yXOPE63UDYWW\/va3ot.3V.C.eFRy415L\/avh85lLZd4VV3gAQ4t6K",
        "address": "amman",
        "country": "jordan",
        "code": "1234",
        "email": "testing@ex.com",
        "sex": "male",
        "checkbox": "english",
        "about": "testing"
    },
    {
        "username": "ahmad",
        "password": "$2y$10$QhCXE2peSiXsooXs3P6WauR.uVmZxyGt2DMpBHlgMvlxD\/CqLTpE6",
        "country": "jordan",
        "email": "ahmad@ex.com"
    }
]